pix_mclass/__init__.py
pix_mclass/losses.py
pix_mclass/training.py
pix_mclass/unet.py
pix_mclass/utils.py
pixmclass-0.1.5.dist-info/licenses/LICENSE.txt
pixmclass-0.1.5.dist-info/METADATA
pixmclass-0.1.5.dist-info/WHEEL
pixmclass-0.1.5.dist-info/top_level.txt
pixmclass-0.1.5.dist-info/RECORD
