Metadata-Version: 2.4
Name: PixMClass
Version: 0.1.5
Summary: Multiclass pixel classification
Home-page: https://github.com/jeanollion/pix_mclass
Download-URL: https://github.com/jeanollion/pix_mclass/releases/download/v0.1.5/pix_mclass-0.1.5.tar.gz
Author: Jean Ollion
Author-email: jean.ollion@sabilab.fr
Keywords: Segmentation,Classification,Microscopy,Cell
Classifier: Development Status :: 4 - Beta
Classifier: Intended Audience :: Science/Research
Classifier: Topic :: Scientific/Engineering :: Artificial Intelligence
Classifier: Topic :: Scientific/Engineering :: Image Processing
Classifier: License :: OSI Approved :: GNU General Public License v3 or later (GPLv3+)
Classifier: Programming Language :: Python :: 3
Requires-Python: >=3
License-File: LICENSE.txt
Requires-Dist: numpy
Requires-Dist: scipy
Requires-Dist: tensorflow>=2.7.1
Requires-Dist: dataset_iterator>=0.5.5
Requires-Dist: elasticdeform>=0.4.7
Dynamic: author
Dynamic: author-email
Dynamic: classifier
Dynamic: description
Dynamic: description-content-type
Dynamic: download-url
Dynamic: home-page
Dynamic: keywords
Dynamic: license-file
Dynamic: requires-dist
Dynamic: requires-python
Dynamic: summary
